amazon_services/__init__.py
amazon_services/amazon_manager.py
amazon_services/login.py
utils/__init__.py
utils/driver.py
utils/gmail_helper.py
utils/webdriver_actions.py
amazon_login-0.7.dist-info/LICENSE
amazon_login-0.7.dist-info/METADATA
amazon_login-0.7.dist-info/WHEEL
amazon_login-0.7.dist-info/top_level.txt
amazon_login-0.7.dist-info/RECORD
