Metadata-Version: 2.1
Name: amazon-login
Version: 0.7
Summary: Log into amazon seller central or vendor central using selenium.
Home-page: http://danielguardado.com
Author: Daniel Guardado
Author-email: danguardado217@gmail.com
License: MIT
Requires-Python: >=3.9
License-File: LICENSE
Requires-Dist: async-generator ==1.10
Requires-Dist: attrs ==23.1.0
Requires-Dist: beautifulsoup4 ==4.12.2
Requires-Dist: bleach ==6.0.0
Requires-Dist: bs4 ==0.0.1
Requires-Dist: cachetools ==5.3.1
Requires-Dist: certifi ==2023.5.7
Requires-Dist: cffi ==1.15.1
Requires-Dist: charset-normalizer ==3.1.0
Requires-Dist: colorama ==0.4.6
Requires-Dist: docutils ==0.20.1
Requires-Dist: exceptiongroup ==1.1.1
Requires-Dist: google-api-core ==2.11.1
Requires-Dist: google-api-python-client ==2.90.0
Requires-Dist: google-auth ==2.21.0
Requires-Dist: google-auth-httplib2 ==0.1.0
Requires-Dist: google-auth-oauthlib ==1.0.0
Requires-Dist: googleapis-common-protos ==1.59.1
Requires-Dist: h11 ==0.14.0
Requires-Dist: httplib2 ==0.22.0
Requires-Dist: idna ==3.4
Requires-Dist: importlib-metadata ==6.7.0
Requires-Dist: jaraco.classes ==3.2.3
Requires-Dist: keyring ==24.2.0
Requires-Dist: lxml ==4.9.2
Requires-Dist: markdown-it-py ==3.0.0
Requires-Dist: mdurl ==0.1.2
Requires-Dist: more-itertools ==9.1.0
Requires-Dist: oauthlib ==3.2.2
Requires-Dist: outcome ==1.2.0
Requires-Dist: packaging ==23.1
Requires-Dist: pkginfo ==1.9.6
Requires-Dist: protobuf ==4.23.3
Requires-Dist: pyasn1 ==0.5.0
Requires-Dist: pyasn1-modules ==0.3.0
Requires-Dist: pycparser ==2.21
Requires-Dist: Pygments ==2.15.1
Requires-Dist: pyparsing ==3.1.0
Requires-Dist: PySocks ==1.7.1
Requires-Dist: python-dotenv ==1.0.0
Requires-Dist: pywin32-ctypes ==0.2.2
Requires-Dist: readme-renderer ==40.0
Requires-Dist: requests ==2.31.0
Requires-Dist: requests-oauthlib ==1.3.1
Requires-Dist: requests-toolbelt ==1.0.0
Requires-Dist: rfc3986 ==2.0.0
Requires-Dist: rich ==13.4.2
Requires-Dist: rsa ==4.9
Requires-Dist: selenium ==4.14.0
Requires-Dist: six ==1.16.0
Requires-Dist: sniffio ==1.3.0
Requires-Dist: sortedcontainers ==2.4.0
Requires-Dist: soupsieve ==2.4.1
Requires-Dist: tqdm ==4.65.0
Requires-Dist: trio ==0.22.0
Requires-Dist: trio-websocket ==0.10.3
Requires-Dist: twine ==4.0.2
Requires-Dist: uritemplate ==4.1.1
Requires-Dist: urllib3 ==1.26.16
Requires-Dist: webdriver-manager ==4.0.1
Requires-Dist: webencodings ==0.5.1
Requires-Dist: wsproto ==1.2.0
Requires-Dist: zipp ==3.15.0
